kotan/__init__.py
kotan/const.py
kotan/job.py
kotan/tasks/__init__.py
kotan/tasks/data_augmentation.py
kotan/tasks/machine_translation.py
kotan/tasks/style_convert.py
kotan-1.1.3.dist-info/METADATA
kotan-1.1.3.dist-info/WHEEL
kotan-1.1.3.dist-info/RECORD
