Metadata-Version: 2.1
Name: kotan
Version: 1.1.3
Summary: 
Author: jisukim
Author-email: jisukim8873@gmail.com
Requires-Python: >=3.8,<4.0
Classifier: Programming Language :: Python :: 3
Classifier: Programming Language :: Python :: 3.8
Classifier: Programming Language :: Python :: 3.9
Classifier: Programming Language :: Python :: 3.10
Classifier: Programming Language :: Python :: 3.11
Requires-Dist: konlpy (==0.6.0)
Requires-Dist: sentencepiece (>=0.1.99,<0.2.0)
Requires-Dist: torch (==2.0.0)
Requires-Dist: transformers (>=4.29.1,<5.0.0)
